odoo/addons/product_pricelist_fixed_currency_rate/README.rst
odoo/addons/product_pricelist_fixed_currency_rate/__init__.py
odoo/addons/product_pricelist_fixed_currency_rate/__manifest__.py
odoo/addons/product_pricelist_fixed_currency_rate/i18n/es.po
odoo/addons/product_pricelist_fixed_currency_rate/i18n/it.po
odoo/addons/product_pricelist_fixed_currency_rate/i18n/product_pricelist_fixed_currency_rate.pot
odoo/addons/product_pricelist_fixed_currency_rate/models/__init__.py
odoo/addons/product_pricelist_fixed_currency_rate/models/product_pricelist_item.py
odoo/addons/product_pricelist_fixed_currency_rate/models/res_currency.py
odoo/addons/product_pricelist_fixed_currency_rate/readme/CONTRIBUTORS.md
odoo/addons/product_pricelist_fixed_currency_rate/readme/DESCRIPTION.md
odoo/addons/product_pricelist_fixed_currency_rate/readme/USAGE.md
odoo/addons/product_pricelist_fixed_currency_rate/static/description/icon.png
odoo/addons/product_pricelist_fixed_currency_rate/static/description/index.html
odoo/addons/product_pricelist_fixed_currency_rate/tests/__init__.py
odoo/addons/product_pricelist_fixed_currency_rate/tests/test_product_pricelist_fixed_currency_rate.py
odoo/addons/product_pricelist_fixed_currency_rate/views/pricelist_views.xml
odoo_addon_product_pricelist_fixed_currency_rate-18.0.1.0.0.4.dist-info/METADATA
odoo_addon_product_pricelist_fixed_currency_rate-18.0.1.0.0.4.dist-info/WHEEL
odoo_addon_product_pricelist_fixed_currency_rate-18.0.1.0.0.4.dist-info/top_level.txt
odoo_addon_product_pricelist_fixed_currency_rate-18.0.1.0.0.4.dist-info/RECORD
